<?xml version='1.0' encoding='utf-8'?>
<TextureAtlas imagePath="ScorchedGlitch.png">
<SubTexture name="Down0000" x="582" y="3651" width="594" height="394" frameX="0" frameY="-70" frameWidth="574" frameHeight="445" />
<SubTexture name="Down0001" x="1756" y="3651" width="594" height="390" frameX="0" frameY="-74" frameWidth="574" frameHeight="445" />
<SubTexture name="Down0002" x="3489" y="2232" width="583" height="403" frameX="0" frameY="-61" frameWidth="574" frameHeight="445" />
<SubTexture name="Down0003" x="4095" y="2847" width="583" height="404" frameX="0" frameY="-60" frameWidth="574" frameHeight="445" />
<SubTexture name="Down0004" x="1176" y="3651" width="580" height="392" frameX="-1" frameY="-72" frameWidth="574" frameHeight="445" />
<SubTexture name="Down0005" x="3489" y="2635" width="580" height="402" frameX="-1" frameY="-62" frameWidth="574" frameHeight="445" />
<SubTexture name="Down0006" x="0" y="3651" width="582" height="395" frameX="0" frameY="-69" frameWidth="574" frameHeight="445" />
<SubTexture name="Down0007" x="4095" y="3251" width="582" height="396" frameX="0" frameY="-68" frameWidth="574" frameHeight="445" />
<SubTexture name="Down0008" x="4095" y="2428" width="580" height="419" frameX="0" frameY="-45" frameWidth="574" frameHeight="445" />
<SubTexture name="Down0009" x="4095" y="2428" width="580" height="419" frameX="0" frameY="-45" frameWidth="574" frameHeight="445" />
<SubTexture name="Down0010" x="4095" y="2428" width="580" height="419" frameX="0" frameY="-45" frameWidth="574" frameHeight="445" />
<SubTexture name="Down0011" x="4095" y="2428" width="580" height="419" frameX="0" frameY="-45" frameWidth="574" frameHeight="445" />
<SubTexture name="Down0012" x="4095" y="2428" width="580" height="419" frameX="0" frameY="-45" frameWidth="574" frameHeight="445" />
<SubTexture name="Down0013" x="4095" y="2428" width="580" height="419" frameX="0" frameY="-45" frameWidth="574" frameHeight="445" />
<SubTexture name="Down0014" x="4095" y="2428" width="580" height="419" frameX="0" frameY="-45" frameWidth="574" frameHeight="445" />
<SubTexture name="Idle0000" x="2232" y="0" width="404" height="614" frameX="0" frameY="-32" frameWidth="470" frameHeight="626" />
<SubTexture name="Idle0001" x="0" y="1933" width="420" height="614" frameX="0" frameY="-32" frameWidth="470" frameHeight="626" />
<SubTexture name="Idle0002" x="980" y="1933" width="455" height="606" frameX="0" frameY="-40" frameWidth="470" frameHeight="626" />
<SubTexture name="Idle0003" x="1435" y="1933" width="446" height="606" frameX="0" frameY="-40" frameWidth="470" frameHeight="626" />
<SubTexture name="Idle0004" x="2636" y="0" width="439" height="605" frameX="-1" frameY="-41" frameWidth="470" frameHeight="626" />
<SubTexture name="Idle0005" x="1881" y="1933" width="431" height="606" frameX="-1" frameY="-40" frameWidth="470" frameHeight="626" />
<SubTexture name="Idle0006" x="3075" y="602" width="414" height="600" frameX="-1" frameY="-46" frameWidth="470" frameHeight="626" />
<SubTexture name="Idle0007" x="1750" y="1309" width="413" height="615" frameX="-1" frameY="-31" frameWidth="470" frameHeight="626" />
<SubTexture name="Idle0008" x="2636" y="1210" width="426" height="602" frameX="0" frameY="-44" frameWidth="470" frameHeight="626" />
<SubTexture name="Idle0009" x="2636" y="1812" width="414" height="602" frameX="0" frameY="-44" frameWidth="470" frameHeight="626" />
<SubTexture name="Idle0010" x="1696" y="626" width="391" height="624" frameX="0" frameY="-22" frameWidth="470" frameHeight="626" />
<SubTexture name="Idle0011" x="0" y="1309" width="409" height="624" frameX="0" frameY="-22" frameWidth="470" frameHeight="626" />
<SubTexture name="Idle0012" x="2636" y="605" width="407" height="605" frameX="0" frameY="-41" frameWidth="470" frameHeight="626" />
<SubTexture name="Idle0013" x="3075" y="1202" width="363" height="600" frameX="0" frameY="-46" frameWidth="470" frameHeight="626" />
<SubTexture name="Idle0014" x="1396" y="2547" width="422" height="600" frameX="0" frameY="-46" frameWidth="470" frameHeight="626" />
<SubTexture name="Idle0015" x="3075" y="0" width="414" height="602" frameX="0" frameY="-44" frameWidth="470" frameHeight="626" />
<SubTexture name="Idle0016" x="409" y="1309" width="394" height="624" frameX="0" frameY="-22" frameWidth="470" frameHeight="626" />
<SubTexture name="Idle0017" x="803" y="1309" width="411" height="624" frameX="0" frameY="-22" frameWidth="470" frameHeight="626" />
<SubTexture name="Idle0018" x="0" y="2547" width="426" height="602" frameX="0" frameY="-44" frameWidth="470" frameHeight="626" />
<SubTexture name="Idle0019" x="426" y="2547" width="416" height="602" frameX="0" frameY="-44" frameWidth="470" frameHeight="626" />
<SubTexture name="Left0000" x="2385" y="2547" width="591" height="580" frameX="-24" frameY="-70" frameWidth="596" frameHeight="634" />
<SubTexture name="Left0001" x="3489" y="577" width="591" height="565" frameX="-24" frameY="-85" frameWidth="596" frameHeight="634" />
<SubTexture name="Left0002" x="4095" y="492" width="606" height="485" frameX="0" frameY="-165" frameWidth="596" frameHeight="634" />
<SubTexture name="Left0003" x="3489" y="0" width="606" height="577" frameX="0" frameY="-73" frameWidth="596" frameHeight="634" />
<SubTexture name="Left0004" x="3489" y="1142" width="584" height="550" frameX="-23" frameY="-101" frameWidth="596" frameHeight="634" />
<SubTexture name="Left0005" x="3489" y="1692" width="584" height="540" frameX="-23" frameY="-111" frameWidth="596" frameHeight="634" />
<SubTexture name="Left0006" x="1818" y="2547" width="567" height="581" frameX="-46" frameY="-70" frameWidth="596" frameHeight="634" />
<SubTexture name="Left0007" x="1818" y="2547" width="567" height="581" frameX="-46" frameY="-70" frameWidth="596" frameHeight="634" />
<SubTexture name="Left0008" x="842" y="2547" width="554" height="602" frameX="-61" frameY="-49" frameWidth="596" frameHeight="634" />
<SubTexture name="Left0009" x="842" y="2547" width="554" height="602" frameX="-61" frameY="-49" frameWidth="596" frameHeight="634" />
<SubTexture name="Left0010" x="842" y="2547" width="554" height="602" frameX="-61" frameY="-49" frameWidth="596" frameHeight="634" />
<SubTexture name="Left0011" x="842" y="2547" width="554" height="602" frameX="-61" frameY="-49" frameWidth="596" frameHeight="634" />
<SubTexture name="Left0012" x="842" y="2547" width="554" height="602" frameX="-61" frameY="-49" frameWidth="596" frameHeight="634" />
<SubTexture name="Left0013" x="842" y="2547" width="554" height="602" frameX="-61" frameY="-49" frameWidth="596" frameHeight="634" />
<SubTexture name="Left0014" x="842" y="2547" width="554" height="602" frameX="-61" frameY="-49" frameWidth="596" frameHeight="634" />
<SubTexture name="Left0015" x="842" y="2547" width="554" height="602" frameX="-61" frameY="-49" frameWidth="596" frameHeight="634" />
<SubTexture name="Left0016" x="842" y="2547" width="554" height="602" frameX="-61" frameY="-49" frameWidth="596" frameHeight="634" />
<SubTexture name="Left0017" x="842" y="2547" width="554" height="602" frameX="-61" frameY="-49" frameWidth="596" frameHeight="634" />
<SubTexture name="Left0018" x="842" y="2547" width="554" height="602" frameX="-61" frameY="-49" frameWidth="596" frameHeight="634" />
<SubTexture name="Left0019" x="842" y="2547" width="554" height="602" frameX="-61" frameY="-49" frameWidth="596" frameHeight="634" />
<SubTexture name="Right0000" x="0" y="3149" width="779" height="502" frameX="-2" frameY="-8" frameWidth="782" frameHeight="490" />
<SubTexture name="Right0001" x="779" y="3149" width="779" height="502" frameX="-2" frameY="-8" frameWidth="782" frameHeight="490" />
<SubTexture name="Right0002" x="1558" y="3149" width="794" height="498" frameX="-1" frameY="-11" frameWidth="782" frameHeight="490" />
<SubTexture name="Right0003" x="2352" y="3149" width="794" height="498" frameX="-1" frameY="-11" frameWidth="782" frameHeight="490" />
<SubTexture name="Right0004" x="3146" y="3149" width="802" height="492" frameX="0" frameY="-17" frameWidth="782" frameHeight="490" />
<SubTexture name="Right0005" x="4095" y="0" width="802" height="492" frameX="0" frameY="-17" frameWidth="782" frameHeight="490" />
<SubTexture name="Right0006" x="4095" y="1462" width="778" height="483" frameX="0" frameY="-26" frameWidth="782" frameHeight="490" />
<SubTexture name="Right0007" x="4095" y="1945" width="778" height="483" frameX="0" frameY="-26" frameWidth="782" frameHeight="490" />
<SubTexture name="Right0008" x="4095" y="977" width="772" height="485" frameX="0" frameY="-24" frameWidth="782" frameHeight="490" />
<SubTexture name="Right0009" x="4095" y="977" width="772" height="485" frameX="0" frameY="-24" frameWidth="782" frameHeight="490" />
<SubTexture name="Right0010" x="4095" y="977" width="772" height="485" frameX="0" frameY="-24" frameWidth="782" frameHeight="490" />
<SubTexture name="Right0011" x="4095" y="977" width="772" height="485" frameX="0" frameY="-24" frameWidth="782" frameHeight="490" />
<SubTexture name="Right0012" x="4095" y="977" width="772" height="485" frameX="0" frameY="-24" frameWidth="782" frameHeight="490" />
<SubTexture name="Right0013" x="4095" y="977" width="772" height="485" frameX="0" frameY="-24" frameWidth="782" frameHeight="490" />
<SubTexture name="Right0014" x="4095" y="977" width="772" height="485" frameX="0" frameY="-24" frameWidth="782" frameHeight="490" />
<SubTexture name="Up0000" x="0" y="667" width="524" height="642" frameX="-33" frameY="-65" frameWidth="551" frameHeight="687" />
<SubTexture name="Up0001" x="524" y="667" width="524" height="642" frameX="-33" frameY="-65" frameWidth="551" frameHeight="687" />
<SubTexture name="Up0002" x="1136" y="0" width="560" height="654" frameX="-4" frameY="-52" frameWidth="551" frameHeight="687" />
<SubTexture name="Up0003" x="420" y="1933" width="560" height="610" frameX="-4" frameY="-96" frameWidth="551" frameHeight="687" />
<SubTexture name="Up0004" x="0" y="0" width="568" height="667" frameX="0" frameY="-38" frameWidth="551" frameHeight="687" />
<SubTexture name="Up0005" x="568" y="0" width="568" height="667" frameX="0" frameY="-38" frameWidth="551" frameHeight="687" />
<SubTexture name="Up0006" x="1214" y="1309" width="536" height="620" frameX="-26" frameY="-86" frameWidth="551" frameHeight="687" />
<SubTexture name="Up0007" x="1696" y="0" width="536" height="626" frameX="-26" frameY="-80" frameWidth="551" frameHeight="687" />
<SubTexture name="Up0008" x="1048" y="667" width="520" height="637" frameX="-45" frameY="-70" frameWidth="551" frameHeight="687" />
<SubTexture name="Up0009" x="1048" y="667" width="520" height="637" frameX="-45" frameY="-70" frameWidth="551" frameHeight="687" />
<SubTexture name="Up0010" x="1048" y="667" width="520" height="637" frameX="-45" frameY="-70" frameWidth="551" frameHeight="687" />
<SubTexture name="Up0011" x="1048" y="667" width="520" height="637" frameX="-45" frameY="-70" frameWidth="551" frameHeight="687" />
<SubTexture name="Up0012" x="1048" y="667" width="520" height="637" frameX="-45" frameY="-70" frameWidth="551" frameHeight="687" />
<SubTexture name="Up0013" x="1048" y="667" width="520" height="637" frameX="-45" frameY="-70" frameWidth="551" frameHeight="687" />
<SubTexture name="Up0014" x="1048" y="667" width="520" height="637" frameX="-45" frameY="-70" frameWidth="551" frameHeight="687" />
<SubTexture name="Up0015" x="1048" y="667" width="520" height="637" frameX="-45" frameY="-70" frameWidth="551" frameHeight="687" />
</TextureAtlas>
