<?xml version='1.0' encoding='utf-8'?>
<!-- Let's be honest: who even noticed they moved that much?
-DeepStare
-->
<TextureAtlas imagePath="staticNotes_assets.png">
<SubTexture name="blue0000" x="0" y="495" width="166" height="160" frameX="0" frameY="0" frameWidth="166" frameHeight="163" />
<SubTexture name="blue0001" x="166" y="495" width="166" height="160" frameX="0" frameY="0" frameWidth="166" frameHeight="163" />
<SubTexture name="blue0002" x="332" y="495" width="166" height="160" frameX="0" frameY="0" frameWidth="166" frameHeight="163" />
<SubTexture name="blue0003" x="498" y="495" width="166" height="160" frameX="0" frameY="0" frameWidth="166" frameHeight="163" />
<SubTexture name="green0000" x="163" y="166" width="163" height="163" frameX="0" frameY="0" frameWidth="166" frameHeight="163" />
<SubTexture name="green0001" x="486" y="0" width="166" height="163" frameX="0" frameY="0" frameWidth="166" frameHeight="163" />
<SubTexture name="green0002" x="486" y="163" width="166" height="163" frameX="0" frameY="0" frameWidth="166" frameHeight="163" />
<SubTexture name="green0003" x="0" y="332" width="166" height="163" frameX="0" frameY="0" frameWidth="166" frameHeight="163" />
<SubTexture name="purple0000" x="166" y="332" width="163" height="163" frameX="0" frameY="0" frameWidth="163" frameHeight="166" />
<SubTexture name="purple0001" x="326" y="166" width="160" height="163" frameX="0" frameY="0" frameWidth="163" frameHeight="166" />
<SubTexture name="purple0002" x="329" y="332" width="163" height="163" frameX="0" frameY="0" frameWidth="163" frameHeight="166" />
<SubTexture name="purple0003" x="652" y="0" width="163" height="163" frameX="0" frameY="0" frameWidth="163" frameHeight="166" />
<SubTexture name="red0000" x="0" y="0" width="163" height="166" frameX="0" frameY="0" frameWidth="163" frameHeight="166" />
<SubTexture name="red0001" x="163" y="0" width="163" height="166" frameX="0" frameY="0" frameWidth="163" frameHeight="166" />
<SubTexture name="red0002" x="326" y="0" width="160" height="166" frameX="0" frameY="0" frameWidth="163" frameHeight="166" />
<SubTexture name="red0003" x="0" y="166" width="163" height="166" frameX="0" frameY="0" frameWidth="163" frameHeight="166" />
</TextureAtlas>
